qltool/__init__.py
qltool/client.py
qltool/main.py
qltool/data/ql570
qltool/data/ql570.c
qltool-0.2.4.dist-info/METADATA
qltool-0.2.4.dist-info/WHEEL
qltool-0.2.4.dist-info/entry_points.txt
qltool-0.2.4.dist-info/RECORD
