Metadata-Version: 2.4
Name: qltool
Version: 0.2.4
Summary: PRINT simple labels on ql700
Requires-Python: >=3.10
Requires-Dist: click>=8.2.1
Requires-Dist: console>=0.9911
Requires-Dist: importlib-resources>=6.5.2
Requires-Dist: opencv-python>=4.12.0.88
Requires-Dist: paho-mqtt>=2.1.0
Requires-Dist: pillow>=11.3.0
Requires-Dist: qrcode>=8.2
